{
  "title": "Release Notes latest",
  "changes": [
    {
      "file": "computation/serviceDeployment.schema.omi.json",
      "modifiedAttributes": [
        {
          "property": "properties.props:dependsOn.labelPlural"
        },
        {
          "property": "properties.props:dependsOn.namePlural"
        },
        {
          "property": "properties.props:provides.labelPlural"
        },
        {
          "property": "properties.props:provides.namePlural"
        },
        {
          "property": "properties.props:uses.labelPlural"
        },
        {
          "property": "properties.props:uses.namePlural"
        }
      ],
      "schemaType": "ServiceDeployment"
    },
    {
      "file": "computation/validationTestVersion.schema.omi.json",
      "modifiedAttributes": [
        {
          "property": "properties.props:isPrecededBy.labelPlural"
        },
        {
          "property": "properties.props:isPrecededBy.namePlural"
        },
        {
          "property": "properties.props:isVariantOf.labelPlural"
        },
        {
          "property": "properties.props:isVariantOf.namePlural"
        },
        {
          "property": "properties.props:isVersionOf.labelPlural"
        },
        {
          "property": "properties.props:isVersionOf.namePlural"
        }
      ],
      "schemaType": "ValidationTestVersion"
    },
    {
      "file": "computation/workflowRecipeVersion.schema.omi.json",
      "modifiedAttributes": [
        {
          "property": "properties.props:isPrecededBy.labelPlural"
        },
        {
          "property": "properties.props:isPrecededBy.namePlural"
        },
        {
          "property": "properties.props:isVariantOf.labelPlural"
        },
        {
          "property": "properties.props:isVariantOf.namePlural"
        },
        {
          "property": "properties.props:isVersionOf.labelPlural"
        },
        {
          "property": "properties.props:isVersionOf.namePlural"
        }
      ],
      "schemaType": "WorkflowRecipeVersion"
    },
    {
      "file": "core/actors/organization.schema.omi.json",
      "addedAttributes": [
        "properties.props:membership.labelPlural",
        "properties.props:membership.namePlural"
      ],
      "schemaType": "Organization"
    },
    {
      "file": "core/data/contentType.schema.omi.json",
      "modifiedAttributes": [
        {
          "property": "properties.props:isBasedOn.labelPlural"
        },
        {
          "property": "properties.props:isBasedOn.namePlural"
        }
      ],
      "schemaType": "ContentType"
    },
    {
      "file": "core/data/file.schema.omi.json",
      "modifiedAttributes": [
        {
          "property": "properties.props:isPartOf.labelPlural"
        },
        {
          "property": "properties.props:isPartOf.namePlural"
        }
      ],
      "schemaType": "File"
    },
    {
      "file": "core/data/fileBundle.schema.omi.json",
      "modifiedAttributes": [
        {
          "property": "properties.props:isPartOf.labelPlural"
        },
        {
          "property": "properties.props:isPartOf.namePlural"
        }
      ],
      "schemaType": "FileBundle"
    },
    {
      "file": "core/products/datasetVersion.schema.omi.json",
      "modifiedAttributes": [
        {
          "property": "properties.props:isPrecededBy.labelPlural"
        },
        {
          "property": "properties.props:isPrecededBy.namePlural"
        },
        {
          "property": "properties.props:isVariantOf.labelPlural"
        },
        {
          "property": "properties.props:isVariantOf.namePlural"
        },
        {
          "property": "properties.props:isVersionOf.labelPlural"
        },
        {
          "property": "properties.props:isVersionOf.namePlural"
        }
      ],
      "schemaType": "DatasetVersion"
    },
    {
      "file": "core/products/interfaceVersion.schema.omi.json",
      "modifiedAttributes": [
        {
          "property": "properties.props:isPrecededBy.labelPlural"
        },
        {
          "property": "properties.props:isPrecededBy.namePlural"
        },
        {
          "property": "properties.props:isVariantOf.labelPlural"
        },
        {
          "property": "properties.props:isVariantOf.namePlural"
        },
        {
          "property": "properties.props:isVersionOf.labelPlural"
        },
        {
          "property": "properties.props:isVersionOf.namePlural"
        }
      ],
      "schemaType": "InterfaceVersion"
    },
    {
      "file": "core/products/metaDataModelVersion.schema.omi.json",
      "modifiedAttributes": [
        {
          "property": "properties.props:isPrecededBy.labelPlural"
        },
        {
          "property": "properties.props:isPrecededBy.namePlural"
        },
        {
          "property": "properties.props:isVariantOf.labelPlural"
        },
        {
          "property": "properties.props:isVariantOf.namePlural"
        },
        {
          "property": "properties.props:isVersionOf.labelPlural"
        },
        {
          "property": "properties.props:isVersionOf.namePlural"
        }
      ],
      "schemaType": "MetaDataModelVersion"
    },
    {
      "file": "core/products/modelVersion.schema.omi.json",
      "modifiedAttributes": [
        {
          "property": "properties.props:isPrecededBy.labelPlural"
        },
        {
          "property": "properties.props:isPrecededBy.namePlural"
        },
        {
          "property": "properties.props:isVariantOf.labelPlural"
        },
        {
          "property": "properties.props:isVariantOf.namePlural"
        },
        {
          "property": "properties.props:isVersionOf.labelPlural"
        },
        {
          "property": "properties.props:isVersionOf.namePlural"
        }
      ],
      "schemaType": "ModelVersion"
    },
    {
      "file": "core/products/softwareVersion.schema.omi.json",
      "modifiedAttributes": [
        {
          "property": "properties.props:implements.labelPlural"
        },
        {
          "property": "properties.props:implements.namePlural"
        },
        {
          "property": "properties.props:isPrecededBy.labelPlural"
        },
        {
          "property": "properties.props:isPrecededBy.namePlural"
        },
        {
          "property": "properties.props:isVariantOf.labelPlural"
        },
        {
          "property": "properties.props:isVariantOf.namePlural"
        },
        {
          "property": "properties.props:isVersionOf.labelPlural"
        },
        {
          "property": "properties.props:isVersionOf.namePlural"
        }
      ],
      "schemaType": "SoftwareVersion"
    },
    {
      "file": "core/research/protocolExecution.schema.omi.json",
      "modifiedAttributes": [
        {
          "property": "properties.props:isPartOf.labelPlural"
        },
        {
          "property": "properties.props:isPartOf.namePlural"
        }
      ],
      "schemaType": "ProtocolExecution"
    },
    {
      "file": "core/research/subject.schema.omi.json",
      "modifiedAttributes": [
        {
          "property": "properties.props:isPartOf.labelPlural"
        },
        {
          "property": "properties.props:isPartOf.namePlural"
        }
      ],
      "schemaType": "Subject"
    },
    {
      "file": "core/research/subjectGroup.schema.omi.json",
      "modifiedAttributes": [
        {
          "property": "properties.props:isPartOf.labelPlural"
        },
        {
          "property": "properties.props:isPartOf.namePlural"
        },
        {
          "property": "properties.props:numberOfSubjects.labelPlural"
        },
        {
          "property": "properties.props:numberOfSubjects.namePlural"
        }
      ],
      "schemaType": "SubjectGroup"
    },
    {
      "file": "core/research/tissueSample.schema.omi.json",
      "modifiedAttributes": [
        {
          "property": "properties.props:isPartOf.labelPlural"
        },
        {
          "property": "properties.props:isPartOf.namePlural"
        }
      ],
      "schemaType": "TissueSample"
    },
    {
      "file": "core/research/tissueSampleCollection.schema.omi.json",
      "modifiedAttributes": [
        {
          "property": "properties.props:isPartOf.labelPlural"
        },
        {
          "property": "properties.props:isPartOf.namePlural"
        }
      ],
      "schemaType": "TissueSampleCollection"
    },
    {
      "file": "ephys/activity/cellPatching.schema.omi.json",
      "modifiedAttributes": [
        {
          "property": "properties.props:isPartOf.labelPlural"
        },
        {
          "property": "properties.props:isPartOf.namePlural"
        }
      ],
      "schemaType": "CellPatching"
    },
    {
      "file": "ephys/activity/electrodePlacement.schema.omi.json",
      "modifiedAttributes": [
        {
          "property": "properties.props:isPartOf.labelPlural"
        },
        {
          "property": "properties.props:isPartOf.namePlural"
        }
      ],
      "schemaType": "ElectrodePlacement"
    },
    {
      "file": "ephys/activity/recordingActivity.schema.omi.json",
      "modifiedAttributes": [
        {
          "property": "properties.props:isPartOf.labelPlural"
        },
        {
          "property": "properties.props:isPartOf.namePlural"
        }
      ],
      "schemaType": "RecordingActivity"
    },
    {
      "file": "ephys/device/electrodeArray.schema.omi.json",
      "modifiedAttributes": [
        {
          "property": "properties.props:numberOfElectrodes.labelPlural"
        },
        {
          "property": "properties.props:numberOfElectrodes.namePlural"
        }
      ],
      "schemaType": "ElectrodeArray"
    },
    {
      "file": "neuroimaging/activity/dynamicMRIAcquisition.schema.omi.json",
      "addedAttributes": [
        "properties.props:contrastAgent.labelPlural",
        "properties.props:contrastAgent.namePlural",
        "properties.props:delayTime.labelPlural",
        "properties.props:delayTime.namePlural",
        "properties.props:distortionCorrection.labelPlural",
        "properties.props:distortionCorrection.namePlural",
        "properties.props:motionCorrection.labelPlural",
        "properties.props:motionCorrection.namePlural",
        "properties.props:numberOfDiscardedVolumes.labelPlural",
        "properties.props:numberOfDiscardedVolumes.namePlural",
        "properties.props:registrationData.labelPlural",
        "properties.props:registrationData.namePlural",
        "properties.props:specimenOrientation.labelPlural",
        "properties.props:specimenOrientation.namePlural",
        "properties.props:targetAnatomy.labelPlural",
        "properties.props:targetAnatomy.namePlural",
        "properties.props:volumeAcquisitionTime.labelPlural",
        "properties.props:volumeAcquisitionTime.namePlural",
        "properties.props:volumeTiming.labelPlural",
        "properties.props:volumeTiming.namePlural"
      ],
      "modifiedAttributes": [
        {
          "property": "properties.props:isPartOf.labelPlural"
        },
        {
          "property": "properties.props:isPartOf.namePlural"
        }
      ],
      "schemaType": "DynamicMRIAcquisition"
    },
    {
      "file": "neuroimaging/activity/staticMRIAcquisition.schema.omi.json",
      "addedAttributes": [
        "properties.props:contrastAgent.labelPlural",
        "properties.props:contrastAgent.namePlural",
        "properties.props:distortionCorrection.labelPlural",
        "properties.props:distortionCorrection.namePlural",
        "properties.props:motionCorrection.labelPlural",
        "properties.props:motionCorrection.namePlural",
        "properties.props:registrationData.labelPlural",
        "properties.props:registrationData.namePlural",
        "properties.props:specimenOrientation.labelPlural",
        "properties.props:specimenOrientation.namePlural",
        "properties.props:targetAnatomy.labelPlural",
        "properties.props:targetAnatomy.namePlural"
      ],
      "modifiedAttributes": [
        {
          "property": "properties.props:isPartOf.labelPlural"
        },
        {
          "property": "properties.props:isPartOf.namePlural"
        }
      ],
      "schemaType": "StaticMRIAcquisition"
    },
    {
      "file": "neuroimaging/device/MRICoil.schema.omi.json",
      "addedAttributes": [
        "properties.props:elementCount.labelPlural",
        "properties.props:elementCount.namePlural",
        "properties.props:intendedMountingLocation.labelPlural",
        "properties.props:intendedMountingLocation.namePlural",
        "properties.props:mountingType.labelPlural",
        "properties.props:mountingType.namePlural"
      ],
      "schemaType": "MRICoil"
    },
    {
      "file": "neuroimaging/device/MRICoilUsage.schema.omi.json",
      "addedAttributes": [
        "properties.props:activeElement.labelPlural",
        "properties.props:activeElement.namePlural",
        "properties.props:mountingLocation.labelPlural",
        "properties.props:mountingLocation.namePlural",
        "properties.props:signalDirectionality.labelPlural",
        "properties.props:signalDirectionality.namePlural"
      ],
      "schemaType": "MRICoilUsage"
    },
    {
      "file": "neuroimaging/device/MRIScanner.schema.omi.json",
      "addedAttributes": [
        "properties.props:magneticFieldStrength.labelPlural",
        "properties.props:magneticFieldStrength.namePlural"
      ],
      "schemaType": "MRIScanner"
    },
    {
      "file": "neuroimaging/device/MRIScannerUsage.schema.omi.json",
      "addedAttributes": [
        "properties.props:accelerationFactor.labelPlural",
        "properties.props:accelerationFactor.namePlural",
        "properties.props:diffusionEncodingParameters.labelPlural",
        "properties.props:diffusionEncodingParameters.namePlural",
        "properties.props:dwellTime.labelPlural",
        "properties.props:dwellTime.namePlural",
        "properties.props:echoTime.labelPlural",
        "properties.props:echoTime.namePlural",
        "properties.props:fatSuppressionTechnique.labelPlural",
        "properties.props:fatSuppressionTechnique.namePlural",
        "properties.props:fieldOfView.labelPlural",
        "properties.props:fieldOfView.namePlural",
        "properties.props:flipAngle.labelPlural",
        "properties.props:flipAngle.namePlural",
        "properties.props:gradientCorrection.labelPlural",
        "properties.props:gradientCorrection.namePlural",
        "properties.props:inversionTime.labelPlural",
        "properties.props:inversionTime.namePlural",
        "properties.props:matrixSize.labelPlural",
        "properties.props:matrixSize.namePlural",
        "properties.props:MRIWeighting.labelPlural",
        "properties.props:MRIWeighting.namePlural",
        "properties.props:MTPulseShape.labelPlural",
        "properties.props:MTPulseShape.namePlural",
        "properties.props:numberOfDiscardedVolumes.labelPlural",
        "properties.props:numberOfDiscardedVolumes.namePlural",
        "properties.props:numberOfExcitations.labelPlural",
        "properties.props:numberOfExcitations.namePlural",
        "properties.props:numberOfSlices.labelPlural",
        "properties.props:numberOfSlices.namePlural",
        "properties.props:parallelAcquisitionTechnique.labelPlural",
        "properties.props:parallelAcquisitionTechnique.namePlural",
        "properties.props:phaseEncodingDirection.labelPlural",
        "properties.props:phaseEncodingDirection.namePlural",
        "properties.props:receiverBandwidth.labelPlural",
        "properties.props:receiverBandwidth.namePlural",
        "properties.props:repetitionTime.labelPlural",
        "properties.props:repetitionTime.namePlural",
        "properties.props:sliceAngulation.labelPlural",
        "properties.props:sliceAngulation.namePlural",
        "properties.props:sliceGap.labelPlural",
        "properties.props:sliceGap.namePlural",
        "properties.props:sliceOrientation.labelPlural",
        "properties.props:sliceOrientation.namePlural",
        "properties.props:sliceTiming.labelPlural",
        "properties.props:sliceTiming.namePlural",
        "properties.props:spatialEncoding.labelPlural",
        "properties.props:spatialEncoding.namePlural",
        "properties.props:spoilingTechnique.labelPlural",
        "properties.props:spoilingTechnique.namePlural",
        "properties.props:totalReadOutTime.labelPlural",
        "properties.props:totalReadOutTime.namePlural",
        "properties.props:transmitterBandwidth.labelPlural",
        "properties.props:transmitterBandwidth.namePlural",
        "properties.props:usedCoils.labelPlural",
        "properties.props:usedCoils.namePlural"
      ],
      "schemaType": "MRIScannerUsage"
    },
    {
      "file": "publications/chapter.schema.omi.json",
      "modifiedAttributes": [
        {
          "property": "properties.props:isPartOf.labelPlural"
        },
        {
          "property": "properties.props:isPartOf.namePlural"
        }
      ],
      "schemaType": "Chapter"
    },
    {
      "file": "publications/livePaperResourceItem.schema.omi.json",
      "modifiedAttributes": [
        {
          "property": "properties.props:isPartOf.labelPlural"
        },
        {
          "property": "properties.props:isPartOf.namePlural"
        }
      ],
      "schemaType": "LivePaperResourceItem"
    },
    {
      "file": "publications/livePaperSection.schema.omi.json",
      "modifiedAttributes": [
        {
          "property": "properties.props:isPartOf.labelPlural"
        },
        {
          "property": "properties.props:isPartOf.namePlural"
        }
      ],
      "schemaType": "LivePaperSection"
    },
    {
      "file": "publications/livePaperVersion.schema.omi.json",
      "modifiedAttributes": [
        {
          "property": "properties.props:isPrecededBy.labelPlural"
        },
        {
          "property": "properties.props:isPrecededBy.namePlural"
        },
        {
          "property": "properties.props:isVariantOf.labelPlural"
        },
        {
          "property": "properties.props:isVariantOf.namePlural"
        },
        {
          "property": "properties.props:isVersionOf.labelPlural"
        },
        {
          "property": "properties.props:isVersionOf.namePlural"
        }
      ],
      "schemaType": "LivePaperVersion"
    },
    {
      "file": "publications/publicationIssue.schema.omi.json",
      "modifiedAttributes": [
        {
          "property": "properties.props:isPartOf.labelPlural"
        },
        {
          "property": "properties.props:isPartOf.namePlural"
        }
      ],
      "schemaType": "PublicationIssue"
    },
    {
      "file": "publications/publicationVolume.schema.omi.json",
      "modifiedAttributes": [
        {
          "property": "properties.props:isPartOf.labelPlural"
        },
        {
          "property": "properties.props:isPartOf.namePlural"
        }
      ],
      "schemaType": "PublicationVolume"
    },
    {
      "file": "publications/scholarlyArticle.schema.omi.json",
      "modifiedAttributes": [
        {
          "property": "properties.props:isPartOf.labelPlural"
        },
        {
          "property": "properties.props:isPartOf.namePlural"
        }
      ],
      "schemaType": "ScholarlyArticle"
    },
    {
      "file": "SANDS/atlas/anatomicalAtlasVersion.schema.omi.json",
      "modifiedAttributes": [
        {
          "property": "properties.props:isPrecededBy.labelPlural"
        },
        {
          "property": "properties.props:isPrecededBy.namePlural"
        },
        {
          "property": "properties.props:isVariantOf.labelPlural"
        },
        {
          "property": "properties.props:isVariantOf.namePlural"
        },
        {
          "property": "properties.props:isVersionOf.labelPlural"
        },
        {
          "property": "properties.props:isVersionOf.namePlural"
        }
      ],
      "schemaType": "AnatomicalAtlasVersion"
    },
    {
      "file": "SANDS/atlas/commonCoordinateFrameworkVersion.schema.omi.json",
      "modifiedAttributes": [
        {
          "property": "properties.props:isPrecededBy.labelPlural"
        },
        {
          "property": "properties.props:isPrecededBy.namePlural"
        },
        {
          "property": "properties.props:isVariantOf.labelPlural"
        },
        {
          "property": "properties.props:isVariantOf.namePlural"
        },
        {
          "property": "properties.props:isVersionOf.labelPlural"
        },
        {
          "property": "properties.props:isVersionOf.namePlural"
        }
      ],
      "schemaType": "CommonCoordinateFrameworkVersion"
    },
    {
      "file": "SANDS/atlas/parcellationEntityVersion.schema.omi.json",
      "modifiedAttributes": [
        {
          "property": "properties.props:isVersionOf.labelPlural"
        },
        {
          "property": "properties.props:isVersionOf.namePlural"
        }
      ],
      "schemaType": "ParcellationEntityVersion"
    },
    {
      "file": "specimenPrep/activity/cranialWindowPreparation.schema.omi.json",
      "modifiedAttributes": [
        {
          "property": "properties.props:isPartOf.labelPlural"
        },
        {
          "property": "properties.props:isPartOf.namePlural"
        }
      ],
      "schemaType": "CranialWindowPreparation"
    },
    {
      "file": "specimenPrep/activity/tissueCulturePreparation.schema.omi.json",
      "modifiedAttributes": [
        {
          "property": "properties.props:isPartOf.labelPlural"
        },
        {
          "property": "properties.props:isPartOf.namePlural"
        }
      ],
      "schemaType": "TissueCulturePreparation"
    },
    {
      "file": "specimenPrep/activity/tissueSampleSlicing.schema.omi.json",
      "modifiedAttributes": [
        {
          "property": "properties.props:isPartOf.labelPlural"
        },
        {
          "property": "properties.props:isPartOf.namePlural"
        }
      ],
      "schemaType": "TissueSampleSlicing"
    },
    {
      "file": "stimulation/activity/stimulationActivity.schema.omi.json",
      "modifiedAttributes": [
        {
          "property": "properties.props:isPartOf.labelPlural"
        },
        {
          "property": "properties.props:isPartOf.namePlural"
        }
      ],
      "schemaType": "StimulationActivity"
    }
  ]
}
