{
  "_type": "core:NumericalProperty",
  "label": "Core:numerical property",
  "name": "core:NumericalProperty",
  "properties": {
    "https://openminds.ebrains.eu/vocab/name": {
      "_instruction": "Enter a descriptive name for this numerical property.",
      "description": "Word or phrase that constitutes the distinctive designation of a being or thing.",
      "formatting": "text/plain",
      "label": "Name",
      "labelPlural": "Names",
      "multiline": false,
      "name": "name",
      "namePlural": "names",
      "type": "string"
    },
    "https://openminds.ebrains.eu/vocab/value": {
      "_embeddedTypes": [
        "core:QuantitativeValue",
        "core:QuantitativeValueRange"
      ],
      "_instruction": "Enter all quantitative values that are described by this numerical property.",
      "description": "Entry for a property.",
      "label": "Value",
      "labelPlural": "Values",
      "minItems": 1,
      "name": "value",
      "nameForReverseLink": null,
      "namePlural": "values",
      "type": "array"
    }
  },
  "required": [
    "https://openminds.ebrains.eu/vocab/name",
    "https://openminds.ebrains.eu/vocab/value"
  ]
}